add_only_dictionary/__init__.py
add_only_dictionary/aodict.py
add_only_dictionary/aolist.py
add_only_dictionary/py.typed
add_only_dictionary-0.2.0.dist-info/entry_points.txt
add_only_dictionary-0.2.0.dist-info/LICENSE
add_only_dictionary-0.2.0.dist-info/WHEEL
add_only_dictionary-0.2.0.dist-info/METADATA
add_only_dictionary-0.2.0.dist-info/RECORD
