Metadata-Version: 2.1
Name: add-only-dictionary
Version: 0.2.0
Summary: Add Only Dictionary
Home-page: https://github.com/maccam912/add-only-dictionary
License: MIT
Author: Matt Koski
Author-email: maccam912@gmail.com
Requires-Python: >=3.7,<4.0
Classifier: Development Status :: 4 - Beta
Classifier: License :: OSI Approved :: MIT License
Classifier: Programming Language :: Python :: 3
Classifier: Programming Language :: Python :: 3.7
Classifier: Programming Language :: Python :: 3.8
Classifier: Programming Language :: Python :: 3.9
Classifier: Programming Language :: Python :: 3.10
Classifier: Programming Language :: Python :: 3.11
Requires-Dist: click (>=8.0.1)
Project-URL: Changelog, https://github.com/maccam912/add-only-dictionary/releases
Project-URL: Documentation, https://add-only-dictionary.readthedocs.io
Project-URL: Repository, https://github.com/maccam912/add-only-dictionary
